easyplayer/__init__.py
easyplayer/__main__.py
easyplayer/exceptions.py
easyplayer/version.py
easyplayer/core/__init__.py
easyplayer/core/event.py
easyplayer/core/saver.py
easyplayer/core/styles.py
easyplayer/core/window.py
easyplayer/core/widgets/__init__.py
easyplayer/core/widgets/background.py
easyplayer/core/widgets/bar.py
easyplayer/core/widgets/camera.py
easyplayer/core/widgets/canvas.py
easyplayer/core/widgets/label.py
easyplayer/core/widgets/sprite.py
easyplayer/core/widgets/entry/__init__.py
easyplayer/core/widgets/entry/entry.py
easyplayer/core/widgets/video/__init__.py
easyplayer/core/widgets/video/clip.py
easyplayer/core/widgets/video/video.py
easyplayer/utils/__init__.py
easyplayer/utils/color.py
easyplayer/utils/coordinate.py
easyplayer/utils/managers.py
easyplayer/utils/mblock.py
easyplayer/utils/music.py
easyplayer/utils/record.py
easyplayer/utils/screencap.py
easyplayer/utils/screenshot.py
easyplayer/utils/timer.py
easyplayer/utils/cs/__init__.py
easyplayer/utils/cs/client.py
easyplayer/utils/cs/server.py
easyplayer/utils/senior/__init__.py
easyplayer/utils/senior/speak.py
easyplayer/utils/senior/translate.py
easyplayer/utils/senior/chatter/__init__.py
easyplayer/utils/senior/chatter/chinese.py
easyplayer/utils/senior/chatter/english.py
easyplayer/utils/wintools/__init__.py
easyplayer/utils/wintools/browser.py
easyplayer/utils/wintools/calendar.py
easyplayer/utils/wintools/clipboard.py
easyplayer/utils/wintools/inwindow.py
easyplayer/utils/wintools/printscreen.py
easyplayer/utils/wintools/richtext.py
easyplayer-1.0.1.dist-info/LICENSE
easyplayer-1.0.1.dist-info/METADATA
easyplayer-1.0.1.dist-info/WHEEL
easyplayer-1.0.1.dist-info/top_level.txt
easyplayer-1.0.1.dist-info/RECORD
